ssh_terminal_manager/__init__.py
ssh_terminal_manager/error.py
ssh_terminal_manager/manager.py
ssh_terminal_manager/ping.py
ssh_terminal_manager/terminal.py
ssh_terminal_manager-2.0.2.dist-info/licenses/LICENSE
ssh_terminal_manager-2.0.2.dist-info/METADATA
ssh_terminal_manager-2.0.2.dist-info/WHEEL
ssh_terminal_manager-2.0.2.dist-info/top_level.txt
ssh_terminal_manager-2.0.2.dist-info/RECORD
