Metadata-Version: 2.4
Name: ssh_terminal_manager
Version: 2.0.2
Summary: Use terminal commands to control and monitor remote devices
Author-email: zhbjsh <zhbjsh@outlook.com>
Project-URL: Homepage, https://github.com/zhbjsh/ssh-terminal-manager
Project-URL: Bug Tracker, https://github.com/zhbjsh/ssh-terminal-manager/issues
Keywords: ssh,terminal,console,shell,bash,cmd,power shell,commands,command line
Classifier: Programming Language :: Python :: 3.12
Classifier: License :: OSI Approved :: MIT License
Classifier: Operating System :: OS Independent
Requires-Python: >=3.12
License-File: LICENSE
Requires-Dist: icmplib>=3.0
Requires-Dist: paramiko>=3.4.1
Requires-Dist: terminal-manager==2.0.2
Requires-Dist: wakeonlan>=3.0.0
Dynamic: license-file
